[
  {
    "id": 1,
    "nombre": "Remera",
    "categoria": "ropa",
    "talle": "S",
    "precio": 1500,
    "img": "img/remera1.jpg",
    "cantidad": 1
  },
  {
    "id": 2,
    "nombre": "Remera",
    "categoria": "ropa",
    "talle": "M",
    "precio": 1500,
    "img": "img/remera1.jpg",
    "cantidad": 1
  },
  {
    "id": 3,
    "nombre": "Remera",
    "categoria": "ropa",
    "talle": "L",
    "precio": 1500,
    "img": "img/remera1.jpg",
    "cantidad": 1
  },
  {
    "id": 4,
    "nombre": "Remera",
    "categoria": "ropa",
    "talle": "XL",
    "precio": 1500,
    "img": "img/remera1.jpg",
    "cantidad": 1
  },
  {
    "id": 5,
    "nombre": "Buzo",
    "categoria": "ropa",
    "talle": "S",
    "precio": 2200,
    "img": "img/buzo1.jpg",
    "cantidad": 1
  },
  {
    "id": 6,
    "nombre": "Buzo",
    "categoria": "ropa",
    "talle": "M",
    "precio": 2200,
    "img": "img/buzo1.jpg",
    "cantidad": 1
  },
  {
    "id": 7,
    "nombre": "Buzo",
    "categoria": "ropa",
    "talle": "L",
    "precio": 2200,
    "img": "img/buzo1.jpg",
    "cantidad": 1
  },
  {
    "id": 8,
    "nombre": "Buzo",
    "categoria": "ropa",
    "talle": "XL",
    "precio": 2200,
    "img": "img/buzo1.jpg",
    "cantidad": 1
  },
  {
    "id": 9,
    "nombre": "Campera",
    "categoria": "ropa",
    "talle": "S",
    "precio": 2500,
    "img": "img/campera1.jpg",
    "cantidad": 1
  },
  {
    "id": 10,
    "nombre": "Campera",
    "categoria": "ropa",
    "talle": "M",
    "precio": 2500,
    "img": "img/campera1.jpg",
    "cantidad": 1
  },
  {
    "id": 11,
    "nombre": "Campera",
    "categoria": "ropa",
    "talle": "L",
    "precio": 2500,
    "img": "img/campera1.jpg",
    "cantidad": 1
  },
  {
    "id": 12,
    "nombre": "Campera",
    "categoria": "ropa",
    "talle": "XL",
    "precio": 2500,
    "img": "img/campera1.jpg",
    "cantidad": 1
  },
  {
    "id": 13,
    "nombre": "Gorra1",
    "categoria": "accesorios",
    "talle": "",
    "precio": 1200,
    "img": "img/gorra1.jpg",
    "cantidad": 1
  },
  {
    "id": 14,
    "nombre": "Gorra2",
    "categoria": "accesorios",
    "talle": "",
    "precio": 1200,
    "img": "img/gorra1.jpg",
    "cantidad": 1
  },
  {
    "id": 15,
    "nombre": "Cadenita",
    "categoria": "accesorios",
    "talle": "",
    "precio": 800,
    "img": "img/cadenita1.jpg",
    "cantidad": 1
  },
  {
    "id": 16,
    "nombre": "Dije",
    "categoria": "accesorios",
    "talle": "",
    "precio": 1000,
    "img": "img/cadenita1.jpg",
    "cantidad": 1
  },
  {
    "id": 17,
    "nombre": "Cd 1",
    "categoria": "cds",
    "talle": "",
    "precio": 1300,
    "img": "img/cd1.jpg",
    "cantidad": 1
  },
  {
    "id": 18,
    "nombre": "Cd 2",
    "categoria": "cds",
    "talle": "",
    "precio": 1600,
    "img": "img/cd2.jpg",
    "cantidad": 1
  }
]
